htmlfetcher
