Metadata-Version: 1.1
Name: htmlfetcher
Version: 0.0.6
Summary: No pain HTML fetching library.
Home-page: https://github.com/gaojiuli/htmlfetcher
Author: Jiuli Gao
Author-email: gaojiuli@gmail.com
License: UNKNOWN
Platform: UNKNOWN
Classifier: Development Status :: 5 - Production/Stable
Classifier: Intended Audience :: Developers
Classifier: Programming Language :: Python :: 3.5
Classifier: Programming Language :: Python :: 3.6
